dye/__init__.py
dye/__main__.py
dye/agents.py
dye/dye.py
dye/exceptions.py
dye/filters.py
dye/pattern.py
dye/scope.py
dye/theme.py
dye/utils.py
dye_your_shell-0.12.0.dist-info/LICENSE
dye_your_shell-0.12.0.dist-info/METADATA
dye_your_shell-0.12.0.dist-info/WHEEL
dye_your_shell-0.12.0.dist-info/entry_points.txt
dye_your_shell-0.12.0.dist-info/top_level.txt
dye_your_shell-0.12.0.dist-info/RECORD
